poorman_handshake/__init__.py
poorman_handshake/version.py
poorman_handshake/asymmetric/__init__.py
poorman_handshake/asymmetric/utils.py
poorman_handshake/symmetric/__init__.py
poorman_handshake/symmetric/utils.py
poorman_handshake-1.0.1.dist-info/LICENSE.md
poorman_handshake-1.0.1.dist-info/METADATA
poorman_handshake-1.0.1.dist-info/WHEEL
poorman_handshake-1.0.1.dist-info/top_level.txt
poorman_handshake-1.0.1.dist-info/RECORD
